odoo10_addon_l10n_ch_import_pain002-10.0.1.0.0.99.dev3-py2.7-nspkg.pth
odoo/addons/l10n_ch_import_pain002/README.rst
odoo/addons/l10n_ch_import_pain002/__init__.py
odoo/addons/l10n_ch_import_pain002/__manifest__.py
odoo/addons/l10n_ch_import_pain002/i18n/l10n_ch_import_pain002.pot
odoo/addons/l10n_ch_import_pain002/models/__init__.py
odoo/addons/l10n_ch_import_pain002/models/pain002_parser.py
odoo/addons/l10n_ch_import_pain002/static/description/icon.png
odoo/addons/l10n_ch_import_pain002/test_files/pain002p-rejected.xml
odoo/addons/l10n_ch_import_pain002/test_files/test_data.yml
odoo/addons/l10n_ch_import_pain002/tests/__init__.py
odoo/addons/l10n_ch_import_pain002/tests/test_import_pain002.py
odoo10_addon_l10n_ch_import_pain002-10.0.1.0.0.99.dev3.dist-info/METADATA
odoo10_addon_l10n_ch_import_pain002-10.0.1.0.0.99.dev3.dist-info/RECORD
odoo10_addon_l10n_ch_import_pain002-10.0.1.0.0.99.dev3.dist-info/WHEEL
odoo10_addon_l10n_ch_import_pain002-10.0.1.0.0.99.dev3.dist-info/namespace_packages.txt
odoo10_addon_l10n_ch_import_pain002-10.0.1.0.0.99.dev3.dist-info/top_level.txt
