Metadata-Version: 2.1
Name: odoo10-addon-l10n-ch-import-pain002
Version: 10.0.1.0.0.99.dev3
Summary: Import pain002
Home-page: https://www.compassion.ch
Author: Monzione Marco, Odoo Community Association (OCA)
Author-email: support@odoo-community.org
License: AGPL-3
Platform: UNKNOWN
Classifier: Programming Language :: Python
Classifier: Framework :: Odoo
Classifier: License :: OSI Approved :: GNU Affero General Public License v3
Requires-Python: ~=2.7
Requires-Dist: odoo10-addon-account-payment-line-cancel
Requires-Dist: odoo10-addon-account-payment-order
Requires-Dist: odoo (<10.1dev,>=10.0)
